cefc/__init__.py
cefc-0.1.0.dist-info/METADATA
cefc-0.1.0.dist-info/WHEEL
cefc-0.1.0.dist-info/top_level.txt
cefc-0.1.0.dist-info/RECORD
