Metadata-Version: 2.4
Name: cefc
Version: 0.1.0
Summary: A call-effect-commit schema for safe data management in Python
Author-email: maniospas <maniospas@hotmail.com>
License: MIT
Project-URL: Homepage, https://github.com/maniospas/cefc
Project-URL: Documentation, https://github.com/maniospas/cefc#readme
Project-URL: Repository, https://github.com/maniospas/cefc
Keywords: safe execution,metaprogramming,transactional,error handling,services
Classifier: Development Status :: 3 - Alpha
Classifier: Intended Audience :: Developers
Classifier: License :: OSI Approved :: MIT License
Classifier: Programming Language :: Python :: 3
Classifier: Programming Language :: Python :: 3.8
Classifier: Programming Language :: Python :: 3.9
Classifier: Programming Language :: Python :: 3.10
Classifier: Programming Language :: Python :: 3.11
Classifier: Topic :: Software Development :: Libraries
Classifier: Topic :: Utilities
Requires-Python: >=3.8
